pyinform/__init__.py
pyinform/activeinfo.py
pyinform/blockentropy.py
pyinform/conditionalentropy.py
pyinform/dist.py
pyinform/entropyrate.py
pyinform/error.py
pyinform/mutualinfo.py
pyinform/relativeentropy.py
pyinform/shannon.py
pyinform/transferentropy.py
pyinform/inform-1.0.0/lib/linux-x86_64/libinform.so.1.0.0
pyinform/inform-1.0.0/lib/macosx-x86_64/libinform.1.0.0.dylib
pyinform/inform-1.0.0/lib/win-amd64/inform.dll
pyinform/utils/__init__.py
pyinform/utils/binning.py
pyinform/utils/coalesce.py
pyinform/utils/encoding.py
pyinform-0.2.0.dist-info/LICENSE
pyinform-0.2.0.dist-info/METADATA
pyinform-0.2.0.dist-info/WHEEL
pyinform-0.2.0.dist-info/top_level.txt
pyinform-0.2.0.dist-info/RECORD
