Metadata-Version: 1.2
Name: pyinform
Version: 0.2.0
Summary: A wrapper for the Inform library
Home-page: https://github.com/elife-asu/pyinform
Maintainer: Douglas G. Moore
Maintainer-email: doug@dglmoore.com
License: The MIT License (MIT)
